synth_ai-0.7.8.dist-info/METADATA
synth_ai-0.7.8.dist-info/WHEEL
synth_ai-0.7.8.dist-info/entry_points.txt
synth_ai-0.7.8.dist-info/licenses/LICENSE
synth_ai/README.md
synth_ai/__init__.py
synth_ai/__main__.py
synth_ai/cli/README.md
synth_ai/cli/__init__.py
synth_ai/cli/__main__.py
synth_ai/cli/bin.py
synth_ai/cli/commands/harbor/__init__.py
synth_ai/cli/commands/harbor/build.py
synth_ai/cli/commands/harbor/instances.py
synth_ai/cli/commands/harbor/list.py
synth_ai/cli/commands/harbor/run.py
synth_ai/cli/commands/harbor/status.py
synth_ai/cli/commands/harbor/upload.py
synth_ai/cli/commands/localapi/__init__.py
synth_ai/cli/commands/localapi/deploy.py
synth_ai/cli/commands/localapi/serve.py
synth_ai/cli/main.py
synth_ai/cli/prompts.py
synth_ai/cli/setup.py
synth_ai/config/__init__.py
synth_ai/config/supported_models.json
synth_ai/config/supported_models.py
synth_ai/core/README.md
synth_ai/core/__init__.py
synth_ai/core/auth/__init__.py
synth_ai/core/auth/api_key.py
synth_ai/core/auth/device.py
synth_ai/core/auth/setup.py
synth_ai/core/auth/storage.py
synth_ai/core/config/__init__.py
synth_ai/core/config/errors.py
synth_ai/core/config/expansion.py
synth_ai/core/config/resolver.py
synth_ai/core/config/user.py
synth_ai/core/env.py
synth_ai/core/errors.py
synth_ai/core/rust_core/__init__.py
synth_ai/core/rust_core/http.py
synth_ai/core/rust_core/sse.py
synth_ai/core/rust_core/urls.py
synth_ai/core/streaming/__init__.py
synth_ai/core/streaming/config.py
synth_ai/core/streaming/handlers.py
synth_ai/core/streaming/rust_streamer.py
synth_ai/core/streaming/streamer.py
synth_ai/core/streaming/types.py
synth_ai/core/tracing_v3/README.md
synth_ai/core/tracing_v3/__init__.py
synth_ai/core/tracing_v3/abstractions.py
synth_ai/core/tracing_v3/config.py
synth_ai/core/tracing_v3/constants.py
synth_ai/core/tracing_v3/decorators.py
synth_ai/core/tracing_v3/hooks.py
synth_ai/core/tracing_v3/llm_call_record_helpers.py
synth_ai/core/tracing_v3/lm_call_record_abstractions.py
synth_ai/core/tracing_v3/rust_tracer.py
synth_ai/core/tracing_v3/serialization.py
synth_ai/core/tracing_v3/session_tracer.py
synth_ai/core/tracing_v3/sqld.py
synth_ai-0.7.8.dist-info/RECORD
