Metadata-Version: 2.4
Name: synth-ai
Version: 0.7.8
Requires-Dist: pydantic>=2.0.0
Requires-Dist: requests>=2.32.3
Requires-Dist: tqdm>=4.66.4
Requires-Dist: typing-extensions>=4.0.0
Requires-Dist: rich>=13.9.0
Requires-Dist: openai>=1.99.0
Requires-Dist: fastapi>=0.115.12
Requires-Dist: uvicorn>=0.34.2
Requires-Dist: numpy>=2.2.3
Requires-Dist: sqlalchemy>=2.0.42
Requires-Dist: pynacl>=1.5.0
Requires-Dist: click>=8.1.7,<8.2
Requires-Dist: aiohttp>=3.8.0
Requires-Dist: nest-asyncio>=1.6.0
Requires-Dist: httpx>=0.28.1
Requires-Dist: datasets>=4.0.0
Requires-Dist: daytona-sdk>=0.130.0
Requires-Dist: jsonschema>=4.23.0
Requires-Dist: openenv>=0.1.13
Requires-Dist: anthropic>=0.42.0 ; extra == 'providers'
Requires-Dist: groq>=0.30.0 ; extra == 'providers'
Requires-Dist: google-genai>=1.26.0 ; extra == 'providers'
Requires-Dist: build>=1.2.2.post1 ; extra == 'dev'
Requires-Dist: twine>=4.0.0 ; extra == 'dev'
Requires-Dist: keyring>=24.0.0 ; extra == 'dev'
Requires-Dist: pytest>=8.3.3 ; extra == 'dev'
Requires-Dist: pytest-xdist>=3.6.1 ; extra == 'dev'
Requires-Dist: pytest-timeout>=2.3.1 ; extra == 'dev'
Requires-Dist: pytest-asyncio>=0.24.0 ; extra == 'dev'
Requires-Dist: pytest-cov>=4.1.0 ; extra == 'dev'
Requires-Dist: pyright>=1.1.350 ; extra == 'dev'
Requires-Dist: coverage[toml]>=7.3.0 ; extra == 'dev'
Requires-Dist: ruff>=0.1.0 ; extra == 'dev'
Requires-Dist: papermill>=2.6.0 ; extra == 'dev'
Requires-Dist: nest-asyncio>=1.6.0 ; extra == 'dev'
Requires-Dist: crafter>=1.8.3 ; extra == 'research'
Requires-Dist: datasets>=4.0.0 ; extra == 'research'
Requires-Dist: morphcloud>=0.1.3 ; extra == 'swe'
Requires-Dist: swebench>=2.3.0 ; extra == 'swe'
Requires-Dist: anthropic>=0.42.0 ; extra == 'all'
Requires-Dist: groq>=0.30.0 ; extra == 'all'
Requires-Dist: google-genai>=1.26.0 ; extra == 'all'
Requires-Dist: crafter>=1.8.3 ; extra == 'all'
Requires-Dist: datasets>=4.0.0 ; extra == 'all'
Requires-Dist: morphcloud>=0.1.3 ; extra == 'all'
Requires-Dist: swebench>=2.3.0 ; extra == 'all'
Requires-Dist: pyboy>=2.6.0 ; extra == 'all'
Requires-Dist: transformers>=4.56.1 ; extra == 'all'
Requires-Dist: redis>=6.2.0 ; extra == 'all'
Requires-Dist: pandas>=2.2.3 ; extra == 'analytics'
Provides-Extra: schemas
Provides-Extra: providers
Provides-Extra: dev
Provides-Extra: research
Provides-Extra: swe
Provides-Extra: all
Provides-Extra: analytics
License-File: LICENSE
Summary: Serverless Posttraining for Agents - Core AI functionality and tracing
Author-email: Synth AI <josh@usesynth.ai>
License: MIT
Requires-Python: >=3.11
Project-URL: Homepage, https://github.com/synth-laboratories/synth-ai
Project-URL: Repository, https://github.com/synth-laboratories/synth-ai
Project-URL: Issues, https://github.com/synth-laboratories/synth-ai/issues
